pyfilestructuredemo/__init__.py
pyfilestructuredemo/add.py
pyfilestructuredemo/file/__init__.py
pyfilestructuredemo/file/getPath.py
pyfilestructuredemo-0.0.4.dist-info/METADATA
pyfilestructuredemo-0.0.4.dist-info/WHEEL
pyfilestructuredemo-0.0.4.dist-info/top_level.txt
pyfilestructuredemo-0.0.4.dist-info/RECORD
